README.md
setup.py
allinpay/__init__.py
allinpay/allin_authcodetouserid.py
allinpay/allin_cancel.py
allinpay/allin_pay.py
allinpay/allin_query.py
allinpay/allin_refund.py
allinpay/allin_utils.py
allinpay/allin_wxfacepayinfo.py
allinpay.egg-info/PKG-INFO
allinpay.egg-info/SOURCES.txt
allinpay.egg-info/dependency_links.txt
allinpay.egg-info/top_level.txt