Metadata-Version: 1.0
Name: allinpay
Version: 0.0.3
Summary: 通联支付python工具
Home-page: https://github.com/l616769490/allinapy
Author: lijin
Author-email: lijin@dingtalk.com
License: MIT Licence
Keywords: pip,pathtool,timetool,magetool,mage
Platform: any
